README.md
setup.cfg
setup.py
WhyPy.egg-info/PKG-INFO
WhyPy.egg-info/SOURCES.txt
WhyPy.egg-info/dependency_links.txt
WhyPy.egg-info/top_level.txt
whypy/__init__.py
whypy/__packages/__init__.py
whypy/__packages/grafic/__init__.py
whypy/__packages/inference/__init__.py
whypy/__packages/inference/infer_steadystate_bivariate_anm.py
whypy/__packages/inference/infer_steadystate_mvariate_anm.py
whypy/__packages/inference/infer_transient_bivariate_anm.py
whypy/__packages/inference/infer_transient_mvariate_anm.py
whypy/__packages/inference/module_anm.py
whypy/__packages/inference/module_general.py
whypy/__packages/inference/module_time.py
whypy/__packages/inference/module_variate.py
whypy/__packages/load/__init__.py
whypy/__packages/load/model.py
whypy/__packages/load/observations.py
whypy/__packages/load/scaler.py
whypy/__packages/utils/__init__.py
whypy/__packages/utils/hsic_gam.py
whypy/__packages/utils/stats.py
whypy/__packages/utils/utils.py
whypy/load/__init__.py
whypy/steadystate/__init__.py
whypy/steadystate/bivariate/__init__.py
whypy/steadystate/mvariate/__init__.py
whypy/transient/__init__.py
whypy/transient/bivariate/__init__.py
whypy/transient/bivariate/ANM/__init__.py
whypy/transient/mvariate/__init__.py