Metadata-Version: 2.1
Name: WhyPy
Version: 0.1.0
Summary: Toolbox for Causal Inference with Additive Noise Models
Home-page: https://github.com/HoChiak/whypy
Author: HoChiak
Author-email: hochiak.whypy@gmail.com
License: UNKNOWN
Platform: UNKNOWN
Classifier: Programming Language :: Python :: 3
Classifier: License :: OSI Approved :: MIT License
Classifier: Operating System :: OS Independent
